{"cameraMode":{"drawMode":0,"name":"Shaded","section":"Shading Mode"},"sceneLighting":false,"audioPlay":false,"sceneViewState":{"m_AlwaysRefresh":false,"showFog":true,"showSkybox":false,"showFlares":true,"showImageEffects":true,"showParticleSystems":true,"showVisualEffectGraphs":true,"m_FxEnabled":false},"in2DMode":false,"pivot":{"x":0.0,"y":1.5,"z":0.0},"rotation":{"x":-0.3548043966293335,"y":-0.08287689089775086,"z":0.031594060361385348,"w":-0.9307529926300049},"size":1.5913333892822266,"orthographic":false}